requirementslib/__init__.py
requirementslib/environment.py
requirementslib/exceptions.py
requirementslib/fileutils.py
requirementslib/funktools.py
requirementslib/utils.py
requirementslib/models/__init__.py
requirementslib/models/common.py
requirementslib/models/dependencies.py
requirementslib/models/lockfile.py
requirementslib/models/markers.py
requirementslib/models/metadata.py
requirementslib/models/old_pip_utils.py
requirementslib/models/pipfile.py
requirementslib/models/project.py
requirementslib/models/requirements.py
requirementslib/models/setup_info.py
requirementslib/models/url.py
requirementslib/models/utils.py
requirementslib/models/vcs.py
requirementslib-3.0.0.dist-info/LICENSE
requirementslib-3.0.0.dist-info/METADATA
requirementslib-3.0.0.dist-info/WHEEL
requirementslib-3.0.0.dist-info/top_level.txt
requirementslib-3.0.0.dist-info/zip-safe
requirementslib-3.0.0.dist-info/RECORD
