Metadata-Version: 2.1
Name: requirementslib
Version: 3.0.0
Summary: A tool for converting between pip-style and pipfile requirements.
Home-page: https://github.com/sarugaku/requirementslib
Author: Dan Ryan
Author-email: dan@danryan.co
Maintainer: Frost Ming
Maintainer-email: mianghong@gmail.com
License: MIT
Keywords: pipfile,requirements.txt,pip,requirementslib,pipenv,lockfile,dependency resolver,resolver,dependencies
Classifier: Development Status :: 5 - Production/Stable
Classifier: Intended Audience :: Developers
Classifier: License :: OSI Approved :: MIT License
Classifier: Programming Language :: Python
Classifier: Programming Language :: Python :: 3
Classifier: Programming Language :: Python :: 3.7
Classifier: Programming Language :: Python :: 3.8
Classifier: Programming Language :: Python :: 3.9
Classifier: Programming Language :: Python :: 3.10
Classifier: Programming Language :: Python :: 3.11
Classifier: Programming Language :: Python :: Implementation :: CPython
Classifier: Programming Language :: Python :: Implementation :: PyPy
Classifier: Topic :: Software Development :: Build Tools
Classifier: Topic :: Software Development :: Libraries :: Python Modules
Classifier: Topic :: Utilities
Requires-Python: >=3.7
Provides-Extra: tests
Provides-Extra: docs
Provides-Extra: dev
License-File: LICENSE
